planktofeatures/__init__.py
planktofeatures/extractors.py
planktofeatures/whoi_v4/__init__.py
planktofeatures/whoi_v4/all.py
planktofeatures/whoi_v4/biovolume.py
planktofeatures/whoi_v4/blob_geometry.py
planktofeatures/whoi_v4/blobs.py
planktofeatures/whoi_v4/hog.py
planktofeatures/whoi_v4/matlab_compatible_random.py
planktofeatures/whoi_v4/morphology.py
planktofeatures/whoi_v4/perimeter.py
planktofeatures/whoi_v4/phasecong.py
planktofeatures/whoi_v4/ringwedge.py
planktofeatures/whoi_v4/segmentation.py
planktofeatures/whoi_v4/texture.py
planktofeatures-0.1.dist-info/licenses/LICENSE
planktofeatures-0.1.dist-info/METADATA
planktofeatures-0.1.dist-info/WHEEL
planktofeatures-0.1.dist-info/top_level.txt
planktofeatures-0.1.dist-info/RECORD
