Metadata-Version: 2.4
Name: planktofeatures
Version: 0.1
Summary: A Python module for creating morphometric feature information for plankton data.
Author-email: Alex Baldwin <contact@alexbaldwin.dev>
License: LGPL-3.0
Project-URL: Homepage, https://github.com/NOC-OI/planktofeatures
Project-URL: Issues, https://github.com/NOC-OI/planktofeatures/issues
Classifier: Programming Language :: Python :: 3
Classifier: Operating System :: OS Independent
Requires-Python: >=3.6
License-File: LICENSE
Requires-Dist: numpy>=1.13.3
Requires-Dist: pillow>=8.3.1
Requires-Dist: pandas
Requires-Dist: scipy
Requires-Dist: scikit-image
Requires-Dist: phasepack
Requires-Dist: pyfftw
Requires-Dist: scikit-learn
Dynamic: license-file
